Workbook
Name ListaStatus: Listas!$A$2:$A$6
Name ListaPrioridade: Listas!$B$2:$B$4
Name ListaSimNao: Listas!$C$2:$C$3
Name ListaCatRisco: Listas!$D$2:$D$7
Name ListaEstrategia: Listas!$E$2:$E$7
Name ListaStatusRisco: Listas!$F$2:$F$5
Name ListaStatusMudanca: Listas!$G$2:$G$6
Name ListaStatusQuestao: Listas!$H$2:$H$5
Name ListaEngajamento: Listas!$I$2:$I$6
Name ListaFase: Listas!$J$2:$J$6
Name ListaCatLicao: Listas!$K$2:$K$7
Name Lista15: Listas!$L$2:$L$6

Sheet 📊 Dashboard
B2: DASHBOARD EXECUTIVO DO PROJETO
B3: ='📋 TAP'!C4&" | GP: "&'📋 TAP'!C6&" | Atualizado em: "&DAY(TODAY())&"/"&MONTH(TODAY())&"/"&YEAR(TODAY())
B5: SAÚDE GERAL | D5: AVANÇO FÍSICO | G5: SPI (PRAZO) | I5: CPI (CUSTO) | L5: DIAS P/ TÉRMINO | N5: RISCOS CRÍT.+ALTOS
B6: =IF(AND('💰 EVM'!N13>=0.95,'💰 EVM'!M13>=0.95),"🟢 NO RUMO",IF(OR('💰 EVM'!N13<0.85,'💰 EVM'!M13<0.85),"🔴 CRÍTICO","🟡 ATENÇÃO")) | D6: =AVERAGE('📅 Cronograma'!$I$5:$I$25) | G6: ='💰 EVM'!M13 | I6: ='💰 EVM'!N13 | L6: ='📋 TAP'!C9-TODAY() | N6: =SUMPRODUCT(--(ISNUMBER(SEARCH("Crítico",'⚠️ Riscos'!$H$4:$H$33))))+SUMPRODUCT(--(ISNUMBER(SEARCH("Alto",'⚠️ Riscos'!$H$4:$H$33))))
B9: TAREFAS DO CRONOGRAMA | G9: RISCOS ABERTOS POR NÍVEL | L9: PENDÊNCIAS E MUDANÇAS
B10: ✅ Concluídas | C10: =COUNTIF('📅 Cronograma'!$J$5:$J$55,"*Concluída*") | E10: =IFERROR(C10/SUM($C$10:$C$13),0) | G10: 🔴 Crítico | H10: =SUMPRODUCT(--(ISNUMBER(SEARCH("Crítico",'⚠️ Riscos'!$H$4:$H$33))),--('⚠️ Riscos'!$L$4:$L$33<>"Encerrado")) | L10: Questões abertas | N10: =SUMPRODUCT(--('🚧 Questões'!$H$4:$H$29<>""),--('🚧 Questões'!$H$4:$H$29<>"Resolvida"))
B11: 🟡 Em Andamento | C11: =COUNTIF('📅 Cronograma'!$J$5:$J$55,"*Em Andamento*") | E11: =IFERROR(C11/SUM($C$10:$C$13),0) | G11: 🟠 Alto | H11: =SUMPRODUCT(--(ISNUMBER(SEARCH("Alto",'⚠️ Riscos'!$H$4:$H$33))),--('⚠️ Riscos'!$L$4:$L$33<>"Encerrado")) | L11: Questões escaladas | N11: =COUNTIF('🚧 Questões'!$H$4:$H$29,"Escalada")
B12: 🔴 Atrasadas | C12: =COUNTIF('📅 Cronograma'!$J$5:$J$55,"*Atrasada*") | E12: =IFERROR(C12/SUM($C$10:$C$13),0) | G12: 🟡 Moderado | H12: =SUMPRODUCT(--(ISNUMBER(SEARCH("Moderado",'⚠️ Riscos'!$H$4:$H$33))),--('⚠️ Riscos'!$L$4:$L$33<>"Encerrado")) | L12: Mudanças em análise | N12: =COUNTIF('🔄 Mudanças'!$J$4:$J$22,"Em Análise")
B13: ⚪ Não Iniciadas | C13: =COUNTIF('📅 Cronograma'!$J$5:$J$55,"*Não Iniciada*") | E13: =IFERROR(C13/SUM($C$10:$C$13),0) | G13: 🟢 Baixo | H13: =SUMPRODUCT(--(ISNUMBER(SEARCH("Baixo",'⚠️ Riscos'!$H$4:$H$33))),--('⚠️ Riscos'!$L$4:$L$33<>"Encerrado")) | L13: Custo de mudanças aprov. | N13: =SUMIFS('🔄 Mudanças'!$H$4:$H$22,'🔄 Mudanças'!$J$4:$J$22,"Aprovada")
B15: RESUMO FINANCEIRO (EVM) | G15: PRÓXIMOS MARCOS
B16: Orçamento (BAC) | C16: ='💰 EVM'!E13 | G16: ='📅 Cronograma'!C16 | I16: ='📅 Cronograma'!G16 | J16: ='📅 Cronograma'!J16
B17: Valor Agregado (EV) | C17: ='💰 EVM'!I13 | G17: ='📅 Cronograma'!C18 | I17: ='📅 Cronograma'!G18 | J17: ='📅 Cronograma'!J18
B18: Custo Real (AC) | C18: ='💰 EVM'!J13 | G18: ='📅 Cronograma'!C23 | I18: ='📅 Cronograma'!G23 | J18: ='📅 Cronograma'!J23
B19: Projeção Final (EAC) | C19: ='💰 EVM'!O13 | G19: ='📅 Cronograma'!C25 | I19: ='📅 Cronograma'!G25 | J19: ='📅 Cronograma'!J25
B20: Desvio Final (VAC) | C20: ='💰 EVM'!Q13

Sheet 📋 TAP
B2: TERMO DE ABERTURA DO PROJETO (PROJECT CHARTER)
B4: Nome do Projeto | C4: Implantação do Sistema ERP Corporativo
B5: Código do Projeto | C5: PRJ-2026-014
B6: Gerente do Projeto | C6: Ana Beatriz Souza
B7: Patrocinador | C7: Carlos Mendes (Diretor de Operações)
B8: Data de Início | C8: 46083 | D8: Cliente / Área Demandante | E8: Diretoria de Operações
B9: Data de Término | C9: 46325 | D9: Prioridade Estratégica | E9: 🔴 Alta
B10: Orçamento Aprovado | C10: 850000 | D10: Reserva de Contingência | E10: 85000
B12: JUSTIFICATIVA DO PROJETO
B13: Os sistemas legados não se integram, geram retrabalho de ~1.200 h/mês e impedem o fechamento contábil em menos de 12 dias. A implantação do ERP unifica os processos de finanças, suprimentos e vendas, com payback estimado em 18 meses.
B15: OBJETIVO (SMART)
B16: Implantar o ERP nos módulos Financeiro, Suprimentos e Vendas para 320 usuários, até 30/10/2026, com orçamento de R$ 850.000, reduzindo o tempo de fechamento contábil de 12 para 4 dias.
B18: ESCOPO INCLUÍDO
B19: • Módulos Financeiro, Suprimentos e Vendas • Migração de dados dos últimos 5 anos • Treinamento de 320 usuários • 60 dias de operação assistida
B21: ESCOPO EXCLUÍDO (FORA DO ESCOPO)
B22: • Módulos de RH e Manufatura (fase 2) • Integração com e-commerce • Customizações além de 400 h
B24: PREMISSAS
B25: • Key users disponíveis 50% do tempo durante a parametrização • Infraestrutura cloud contratada até abril/2026 • Dados legados entregues pela TI com qualidade mínima acordada
B27: RESTRIÇÕES
B28: • Go-live impreterivelmente antes do fechamento anual (nov/2026) • Orçamento limitado a R$ 850.000 + 10% de contingência • Equipe interna limitada a 8 pessoas dedicadas
... B36: MARCOS PRINCIPAIS
B37: Marco | C37: Data Prevista | D37: Data Real | E37: Status
B38: Kick-off e TAP aprovado | C38: 46094 | D38: 46094 | E38: ✅ Concluída
B39: Plano do projeto aprovado | C39: 46122 | D39: 46126 | E39: ✅ Concluída
B40: Parametrização concluída | C40: 46227 | E40: 🟡 Em Andamento
B41: Migração de dados homologada | C41: 46262 | E41: ⚪ Não Iniciada
B42: Go-live | C42: 46304 | E42: ⚪ Não Iniciada
B43: Encerramento do projeto | C43: 46325 | E43: ⚪ Não Iniciada
B45: APROVAÇÕES
B46: Papel | C46: Nome | D46: Data | E46: Assinatura
B47: Patrocinador | C47: Carlos Mendes
B48: Gerente do Projeto | C48: Ana Beatriz Souza
B49: Cliente / Demandante | C49: Diretoria de Operações

Sheet 🗂️ EAP
A1: EAP — ESTRUTURA ANALÍTICA DO PROJETO (WBS)
A3: Código EAP | B3: Nível | C3: Entrega / Pacote de Trabalho | D3: Responsável | E3: Critério de Aceitação | F3: Descrição
A4: 1 | B4: =LEN(A4)-LEN(SUBSTITUTE(A4,".",""))+1 | C4: Implantação do Sistema ERP Corporativo | D4: Ana B. Souza | F4: Projeto completo
A5: 1.1 | B5: =LEN(A5)-LEN(SUBSTITUTE(A5,".",""))+1 | C5: Gerenciamento do Projeto | D5: Ana B. Souza | E5: Planos aprovados | F5: Iniciação, planos, monitoramento e encerramento
A6: 1.1.1 | B6: =LEN(A6)-LEN(SUBSTITUTE(A6,".",""))+1 | C6: Termo de Abertura (TAP) | D6: Ana B. Souza | E6: Assinado pelo patrocinador
A7: 1.1.2 | B7: =LEN(A7)-LEN(SUBSTITUTE(A7,".",""))+1 | C7: Plano de Gerenciamento do Projeto | D7: Ana B. Souza | E7: Aprovado pelo comitê
A8: 1.2 | B8: =LEN(A8)-LEN(SUBSTITUTE(A8,".",""))+1 | C8: Infraestrutura | D8: Roberto Lima | E8: Ambiente disponível e testado | F8: Cloud, ambientes e acessos
A9: 1.2.1 | B9: =LEN(A9)-LEN(SUBSTITUTE(A9,".",""))+1 | C9: Contratação do ambiente cloud | D9: Roberto Lima | E9: Contrato assinado
A10: 1.2.2 | B10: =LEN(A10)-LEN(SUBSTITUTE(A10,".",""))+1 | C10: Configuração dos ambientes (DEV/QA/PRD) | D10: Roberto Lima | E10: Checklist de infra 100%
A11: 1.3 | B11: =LEN(A11)-LEN(SUBSTITUTE(A11,".",""))+1 | C11: Parametrização do ERP | D11: Fernanda Costa | E11: Processos validados pelos key users | F11: Configuração dos módulos
A12: 1.3.1 | B12: =LEN(A12)-LEN(SUBSTITUTE(A12,".",""))+1 | C12: Módulo Financeiro | D12: Fernanda Costa | E12: Cenários de teste aprovados
A13: 1.3.2 | B13: =LEN(A13)-LEN(SUBSTITUTE(A13,".",""))+1 | C13: Módulo Suprimentos | D13: Diego Martins | E13: Cenários de teste aprovados
A14: 1.3.3 | B14: =LEN(A14)-LEN(SUBSTITUTE(A14,".",""))+1 | C14: Módulo Vendas | D14: Juliana Reis | E14: Cenários de teste aprovados
A15: 1.4 | B15: =LEN(A15)-LEN(SUBSTITUTE(A15,".",""))+1 | C15: Migração de Dados | D15: Roberto Lima | E15: Carga homologada com ≤ 0,5% de erro | F15: Extração, limpeza, carga e validação
A16: 1.4.1 | B16: =LEN(A16)-LEN(SUBSTITUTE(A16,".",""))+1 | C16: Mapeamento e limpeza dos dados | D16: Roberto Lima | E16: De-para aprovado
A17: 1.4.2 | B17: =LEN(A17)-LEN(SUBSTITUTE(A17,".",""))+1 | C17: Cargas de teste e homologação | D17: Roberto Lima | E17: 3 cargas com sucesso
A18: 1.5 | B18: =LEN(A18)-LEN(SUBSTITUTE(A18,".",""))+1 | C18: Testes Integrados | D18: Juliana Reis | E18: 0 defeitos críticos abertos | F18: TIU e testes de aceitação
A19: 1.6 | B19: =LEN(A19)-LEN(SUBSTITUTE(A19,".",""))+1 | C19: Treinamento | D19: Fernanda Costa | E19: 320 usuários treinados, nota ≥ 8 | F19: Material e turmas de capacitação
A20: 1.7 | B20: =LEN(A20)-LEN(SUBSTITUTE(A20,".",""))+1 | C20: Go-live e Operação Assistida | D20: Ana B. Souza | E20: Operação estável por 60 dias | F20: Virada, suporte e estabilização
A21: 1.8 | B21: =LEN(A21)-LEN(SUBSTITUTE(A21,".",""))+1 | C21: Encerramento | D21: Ana B. Souza | E21: Termo de encerramento assinado | F21: Lições aprendidas e transição

Sheet 📅 Cronograma
A1: CRONOGRAMA DO PROJETO — GANTT AUTOMÁTICO
A2: Status, duração e barras do Gantt são 100% automáticos: preencha apenas Início, Término e % Concluído.
A4: ID | B4: EAP | C4: Tarefa / Entrega | D4: Responsável | E4: Prioridade | F4: Início | G4: Término | H4: Duração (dias) | I4: % Concl. | J4: Status (auto) | K4: Predecessoras | L4: Marco? | M4: 46083 | N4: 46090 | O4: 46097 | P4: 46104 | Q4: 46111 | R4: 46118 | S4: 46125 | T4: 46132 | U4: 46139 | V4: 46146 | W4: 46153 | X4: 46160 | Y4: 46167 | Z4: 46174 | AA4: 46181 | AB4: 46188 | AC4: 46195 | AD4: 46202 | AE4: 46209 | AF4: 46216 | AG4: 46223 | AH4: 46230 | AI4: 46237 | AJ4: 46244 | AK4: 46251 | AL4: 46258 | AM4: 46265 | AN4: 46272 | AO4: 46279 | AP4: 46286 | AQ4: 46293 | AR4: 46300 | AS4: 46307 | AT4: 46314 | AU4: 46321 | AV4: 46328
A5: 1 | B5: 1.1.1 | C5: Elaborar e aprovar o TAP | D5: Ana B. Souza | E5: 🔴 Alta | F5: 46083 | G5: 46094 | H5: =IF(OR(F5="",G5=""),"",G5-F5+1) | I5: 1 | J5: =IF(F5="","",IF(I5>=1,"✅ Concluída",IF(TODAY()>G5,"🔴 Atrasada",IF(TODAY()>=F5,"🟡 Em Andamento","⚪ Não Iniciada")))) | L5: Não
A6: 2 | B6: 1.1.1 | C6: 🚩 MARCO: Kick-off do projeto | D6: Ana B. Souza | E6: 🔴 Alta | F6: 46094 | G6: 46094 | H6: =IF(OR(F6="",G6=""),"",G6-F6+1) | I6: 1 | J6: =IF(F6="","",IF(I6>=1,"✅ Concluída",IF(TODAY()>G6,"🔴 Atrasada",IF(TODAY()>=F6,"🟡 Em Andamento","⚪ Não Iniciada")))) | K6: 1 | L6: Sim
A7: 3 | B7: 1.1.2 | C7: Plano de gerenciamento do projeto | D7: Ana B. Souza | E7: 🔴 Alta | F7: 46097 | G7: 46122 | H7: =IF(OR(F7="",G7=""),"",G7-F7+1) | I7: 1 | J7: =IF(F7="","",IF(I7>=1,"✅ Concluída",IF(TODAY()>G7,"🔴 Atrasada",IF(TODAY()>=F7,"🟡 Em Andamento","⚪ Não Iniciada")))) | K7: 2 | L7: Não
A8: 4 | B8: 1.3 | C8: Levantamento de processos (AS-IS/TO-BE) | D8: Fernanda Costa | E8: 🔴 Alta | F8: 46104 | G8: 46136 | H8: =IF(OR(F8="",G8=""),"",G8-F8+1) | I8: 1 | J8: =IF(F8="","",IF(I8>=1,"✅ Concluída",IF(TODAY()>G8,"🔴 Atrasada",IF(TODAY()>=F8,"🟡 Em Andamento","⚪ Não Iniciada")))) | K8: 2 | L8: Não
A9: 5 | B9: 1.2.1 | C9: Contratação do ambiente cloud | D9: Roberto Lima | E9: 🔴 Alta | F9: 46113 | G9: 46142 | H9: =IF(OR(F9="",G9=""),"",G9-F9+1) | I9: 1 | J9: =IF(F9="","",IF(I9>=1,"✅ Concluída",IF(TODAY()>G9,"🔴 Atrasada",IF(TODAY()>=F9,"🟡 Em Andamento","⚪ Não Iniciada")))) | K9: 3 | L9: Não
A10: 6 | B10: 1.2.2 | C10: Configuração dos ambientes DEV/QA/PRD | D10: Roberto Lima | E10: 🟡 Média | F10: 46146 | G10: 46171 | H10: =IF(OR(F10="",G10=""),"",G10-F10+1) | I10: 1 | J10: =IF(F10="","",IF(I10>=1,"✅ Concluída",IF(TODAY()>G10,"🔴 Atrasada",IF(TODAY()>=F10,"🟡 Em Andamento","⚪ Não Iniciada")))) | K10: 5 | L10: Não
A11: 7 | B11: 1.3.1 | C11: Parametrização — Módulo Financeiro | D11: Fernanda Costa | E11: 🔴 Alta | F11: 46146 | G11: 46213 | H11: =IF(OR(F11="",G11=""),"",G11-F11+1) | I11: 0.65 | J11: =IF(F11="","",IF(I11>=1,"✅ Concluída",IF(TODAY()>G11,"🔴 Atrasada",IF(TODAY()>=F11,"🟡 Em Andamento","⚪ Não Iniciada")))) | K11: 4;6 | L11: Não
A12: 8 | B12: 1.3.2 | C12: Parametrização — Módulo Suprimentos | D12: Diego Martins | E12: 🔴 Alta | F12: 46153 | G12: 46220 | H12: =IF(OR(F12="",G12=""),"",G12-F12+1) | I12: 0.55 | J12: =IF(F12="","",IF(I12>=1,"✅ Concluída",IF(TODAY()>G12,"🔴 Atrasada",IF(TODAY()>=F12,"🟡 Em Andamento","⚪ Não Iniciada")))) | K12: 4;6 | L12: Não
A13: 9 | B13: 1.3.3 | C13: Parametrização — Módulo Vendas | D13: Juliana Reis | E13: 🟡 Média | F13: 46160 | G13: 46227 | H13: =IF(OR(F13="",G13=""),"",G13-F13+1) | I13: 0.45 | J13: =IF(F13="","",IF(I13>=1,"✅ Concluída",IF(TODAY()>G13,"🔴 Atrasada",IF(TODAY()>=F13,"🟡 Em Andamento","⚪ Não Iniciada")))) | K13: 4;6 | L13: Não
A14: 10 | B14: 1.4.1 | C14: Mapeamento e limpeza dos dados legados | D14: Roberto Lima | E14: 🔴 Alta | F14: 46153 | G14: 46178 | H14: =IF(OR(F14="",G14=""),"",G14-F14+1) | I14: 0.8 | J14: =IF(F14="","",IF(I14>=1,"✅ Concluída",IF(TODAY()>G14,"🔴 Atrasada",IF(TODAY()>=F14,"🟡 Em Andamento","⚪ Não Iniciada")))) | K14: 6 | L14: Não
A15: 11 | B15: 1.6 | C15: Desenvolvimento do material de treinamento | D15: Fernanda Costa | E15: 🟢 Baixa | F15: 46174 | G15: 46234 | H15: =IF(OR(F15="",G15=""),"",G15-F15+1) | I15: 0.2 | J15: =IF(F15="","",IF(I15>=1,"✅ Concluída",IF(TODAY()>G15,"🔴 Atrasada",IF(TODAY()>=F15,"🟡 Em Andamento","⚪ Não Iniciada")))) | K15: 7 | L15: Não
A16: 12 | B16: 1.3 | C16: 🚩 MARCO: Parametrização concluída | D16: Fernanda Costa | E16: 🔴 Alta | F16: 46227 | G16: 46227 | H16: =IF(OR(F16="",G16=""),"",G16-F16+1) | I16: 0 | J16: =IF(F16="","",IF(I16>=1,"✅ Concluída",IF(TODAY()>G16,"🔴 Atrasada",IF(TODAY()>=F16,"🟡 Em Andamento","⚪ Não Iniciada")))) | K16: 7;8;9 | L16: Sim
A17: 13 | B17: 1.4.2 | C17: Cargas de teste e homologação dos dados | D17: Roberto Lima | E17: 🔴 Alta | F17: 46188 | G17: 46255 | H17: =IF(OR(F17="",G17=""),"",G17-F17+1) | I17: 0.1 | J17: =IF(F17="","",IF(I17>=1,"✅ Concluída",IF(TODAY()>G17,"🔴 Atrasada",IF(TODAY()>=F17,"🟡 Em Andamento","⚪ Não Iniciada")))) | K17: 10 | L17: Não
... A25: 21 | B25: 1.8 | C25: Lições aprendidas e termo de encerramento | D25: Ana B. Souza | E25: 🟡 Média | F25: 46321 | G25: 46325 | H25: =IF(OR(F25="",G25=""),"",G25-F25+1) | I25: 0 | J25: =IF(F25="","",IF(I25>=1,"✅ Concluída",IF(TODAY()>G25,"🔴 Atrasada",IF(TODAY()>=F25,"🟡 Em Andamento","⚪ Não Iniciada")))) | K25: 20 | L25: Não
H26: =IF(OR(F26="",G26=""),"",G26-F26+1) | J26: =IF(F26="","",IF(I26>=1,"✅ Concluída",IF(TODAY()>G26,"🔴 Atrasada",IF(TODAY()>=F26,"🟡 Em Andamento","⚪ Não Iniciada"))))
H27: =IF(OR(F27="",G27=""),"",G27-F27+1) | J27: =IF(F27="","",IF(I27>=1,"✅ Concluída",IF(TODAY()>G27,"🔴 Atrasada",IF(TODAY()>=F27,"🟡 Em Andamento","⚪ Não Iniciada"))))
H28: =IF(OR(F28="",G28=""),"",G28-F28+1) | J28: =IF(F28="","",IF(I28>=1,"✅ Concluída",IF(TODAY()>G28,"🔴 Atrasada",IF(TODAY()>=F28,"🟡 Em Andamento","⚪ Não Iniciada"))))
H29: =IF(OR(F29="",G29=""),"",G29-F29+1) | J29: =IF(F29="","",IF(I29>=1,"✅ Concluída",IF(TODAY()>G29,"🔴 Atrasada",IF(TODAY()>=F29,"🟡 Em Andamento","⚪ Não Iniciada"))))
H30: =IF(OR(F30="",G30=""),"",G30-F30+1) | J30: =IF(F30="","",IF(I30>=1,"✅ Concluída",IF(TODAY()>G30,"🔴 Atrasada",IF(TODAY()>=F30,"🟡 Em Andamento","⚪ Não Iniciada"))))
H31: =IF(OR(F31="",G31=""),"",G31-F31+1) | J31: =IF(F31="","",IF(I31>=1,"✅ Concluída",IF(TODAY()>G31,"🔴 Atrasada",IF(TODAY()>=F31,"🟡 Em Andamento","⚪ Não Iniciada"))))
H32: =IF(OR(F32="",G32=""),"",G32-F32+1) | J32: =IF(F32="","",IF(I32>=1,"✅ Concluída",IF(TODAY()>G32,"🔴 Atrasada",IF(TODAY()>=F32,"🟡 Em Andamento","⚪ Não Iniciada"))))
H33: =IF(OR(F33="",G33=""),"",G33-F33+1) | J33: =IF(F33="","",IF(I33>=1,"✅ Concluída",IF(TODAY()>G33,"🔴 Atrasada",IF(TODAY()>=F33,"🟡 Em Andamento","⚪ Não Iniciada"))))
H34: =IF(OR(F34="",G34=""),"",G34-F34+1) | J34: =IF(F34="","",IF(I34>=1,"✅ Concluída",IF(TODAY()>G34,"🔴 Atrasada",IF(TODAY()>=F34,"🟡 Em Andamento","⚪ Não Iniciada"))))
H35: =IF(OR(F35="",G35=""),"",G35-F35+1) | J35: =IF(F35="","",IF(I35>=1,"✅ Concluída",IF(TODAY()>G35,"🔴 Atrasada",IF(TODAY()>=F35,"🟡 Em Andamento","⚪ Não Iniciada"))))
H36: =IF(OR(F36="",G36=""),"",G36-F36+1) | J36: =IF(F36="","",IF(I36>=1,"✅ Concluída",IF(TODAY()>G36,"🔴 Atrasada",IF(TODAY()>=F36,"🟡 Em Andamento","⚪ Não Iniciada"))))
H37: =IF(OR(F37="",G37=""),"",G37-F37+1) | J37: =IF(F37="","",IF(I37>=1,"✅ Concluída",IF(TODAY()>G37,"🔴 Atrasada",IF(TODAY()>=F37,"🟡 Em Andamento","⚪ Não Iniciada"))))
... H55: =IF(OR(F55="",G55=""),"",G55-F55+1) | J55: =IF(F55="","",IF(I55>=1,"✅ Concluída",IF(TODAY()>G55,"🔴 Atrasada",IF(TODAY()>=F55,"🟡 Em Andamento","⚪ Não Iniciada"))))

Sheet 💰 EVM
A1: EVM — GERENCIAMENTO DE VALOR AGREGADO (EARNED VALUE MANAGEMENT)
A2: Preencha apenas: BAC, % Real e AC. Tudo o mais (PV, EV, SV, CV, SPI, CPI, EAC, ETC, VAC, TCPI) é calculado.
A4: EAP | B4: Pacote de Trabalho | C4: Início | D4: Término | E4: BAC (Orçamento) | F4: % Planej. (auto) | G4: % Real | H4: PV (Valor Planejado) | I4: EV (Valor Agregado) | J4: AC (Custo Real) | K4: SV | L4: CV | M4: SPI | N4: CPI | O4: EAC | P4: ETC | Q4: VAC | R4: TCPI
A5: 1.1 | B5: Gerenciamento do Projeto | C5: 46083 | D5: 46325 | E5: 95000 | F5: =IF(C5="","",MAX(0,MIN(1,(TODAY()-C5+1)/(D5-C5+1)))) | G5: 0.46 | H5: =IF(E5="","",E5*F5) | I5: =IF(E5="","",E5*G5) | J5: 41000 | K5: =IF(E5="","",I5-H5) | L5: =IF(E5="","",I5-J5) | M5: =IFERROR(I5/H5,"—") | N5: =IFERROR(I5/J5,"—") | O5: =IF(E5="","",IFERROR(E5/N5,E5)) | P5: =IF(E5="","",O5-J5) | Q5: =IF(E5="","",E5-O5) | R5: =IFERROR((E5-I5)/(E5-J5),"—")
A6: 1.2 | B6: Infraestrutura | C6: 46113 | D6: 46171 | E6: 120000 | F6: =IF(C6="","",MAX(0,MIN(1,(TODAY()-C6+1)/(D6-C6+1)))) | G6: 1 | H6: =IF(E6="","",E6*F6) | I6: =IF(E6="","",E6*G6) | J6: 131500 | K6: =IF(E6="","",I6-H6) | L6: =IF(E6="","",I6-J6) | M6: =IFERROR(I6/H6,"—") | N6: =IFERROR(I6/J6,"—") | O6: =IF(E6="","",IFERROR(E6/N6,E6)) | P6: =IF(E6="","",O6-J6) | Q6: =IF(E6="","",E6-O6) | R6: =IFERROR((E6-I6)/(E6-J6),"—")
A7: 1.3 | B7: Parametrização do ERP | C7: 46146 | D7: 46227 | E7: 260000 | F7: =IF(C7="","",MAX(0,MIN(1,(TODAY()-C7+1)/(D7-C7+1)))) | G7: 0.55 | H7: =IF(E7="","",E7*F7) | I7: =IF(E7="","",E7*G7) | J7: 158000 | K7: =IF(E7="","",I7-H7) | L7: =IF(E7="","",I7-J7) | M7: =IFERROR(I7/H7,"—") | N7: =IFERROR(I7/J7,"—") | O7: =IF(E7="","",IFERROR(E7/N7,E7)) | P7: =IF(E7="","",O7-J7) | Q7: =IF(E7="","",E7-O7) | R7: =IFERROR((E7-I7)/(E7-J7),"—")
A8: 1.4 | B8: Migração de Dados | C8: 46153 | D8: 46262 | E8: 110000 | F8: =IF(C8="","",MAX(0,MIN(1,(TODAY()-C8+1)/(D8-C8+1)))) | G8: 0.35 | H8: =IF(E8="","",E8*F8) | I8: =IF(E8="","",E8*G8) | J8: 36500 | K8: =IF(E8="","",I8-H8) | L8: =IF(E8="","",I8-J8) | M8: =IFERROR(I8/H8,"—") | N8: =IFERROR(I8/J8,"—") | O8: =IF(E8="","",IFERROR(E8/N8,E8)) | P8: =IF(E8="","",O8-J8) | Q8: =IF(E8="","",E8-O8) | R8: =IFERROR((E8-I8)/(E8-J8),"—")
A9: 1.5 | B9: Testes Integrados | C9: 46237 | D9: 46290 | E9: 90000 | F9: =IF(C9="","",MAX(0,MIN(1,(TODAY()-C9+1)/(D9-C9+1)))) | G9: 0 | H9: =IF(E9="","",E9*F9) | I9: =IF(E9="","",E9*G9) | J9: 0 | K9: =IF(E9="","",I9-H9) | L9: =IF(E9="","",I9-J9) | M9: =IFERROR(I9/H9,"—") | N9: =IFERROR(I9/J9,"—") | O9: =IF(E9="","",IFERROR(E9/N9,E9)) | P9: =IF(E9="","",O9-J9) | Q9: =IF(E9="","",E9-O9) | R9: =IFERROR((E9-I9)/(E9-J9),"—")
A10: 1.6 | B10: Treinamento | C10: 46174 | D10: 46297 | E10: 85000 | F10: =IF(C10="","",MAX(0,MIN(1,(TODAY()-C10+1)/(D10-C10+1)))) | G10: 0.1 | H10: =IF(E10="","",E10*F10) | I10: =IF(E10="","",E10*G10) | J10: 7200 | K10: =IF(E10="","",I10-H10) | L10: =IF(E10="","",I10-J10) | M10: =IFERROR(I10/H10,"—") | N10: =IFERROR(I10/J10,"—") | O10: =IF(E10="","",IFERROR(E10/N10,E10)) | P10: =IF(E10="","",O10-J10) | Q10: =IF(E10="","",E10-O10) | R10: =IFERROR((E10-I10)/(E10-J10),"—")
A11: 1.7 | B11: Go-live e Operação Assistida | C11: 46286 | D11: 46325 | E11: 75000 | F11: =IF(C11="","",MAX(0,MIN(1,(TODAY()-C11+1)/(D11-C11+1)))) | G11: 0 | H11: =IF(E11="","",E11*F11) | I11: =IF(E11="","",E11*G11) | J11: 0 | K11: =IF(E11="","",I11-H11) | L11: =IF(E11="","",I11-J11) | M11: =IFERROR(I11/H11,"—") | N11: =IFERROR(I11/J11,"—") | O11: =IF(E11="","",IFERROR(E11/N11,E11)) | P11: =IF(E11="","",O11-J11) | Q11: =IF(E11="","",E11-O11) | R11: =IFERROR((E11-I11)/(E11-J11),"—")
A12: 1.8 | B12: Encerramento | C12: 46321 | D12: 46325 | E12: 15000 | F12: =IF(C12="","",MAX(0,MIN(1,(TODAY()-C12+1)/(D12-C12+1)))) | G12: 0 | H12: =IF(E12="","",E12*F12) | I12: =IF(E12="","",E12*G12) | J12: 0 | K12: =IF(E12="","",I12-H12) | L12: =IF(E12="","",I12-J12) | M12: =IFERROR(I12/H12,"—") | N12: =IFERROR(I12/J12,"—") | O12: =IF(E12="","",IFERROR(E12/N12,E12)) | P12: =IF(E12="","",O12-J12) | Q12: =IF(E12="","",E12-O12) | R12: =IFERROR((E12-I12)/(E12-J12),"—")
B13: TOTAL DO PROJETO | E13: =SUM(E5:E12) | F13: =H13/E13 | G13: =I13/E13 | H13: =SUM(H5:H12) | I13: =SUM(I5:I12) | J13: =SUM(J5:J12) | K13: =SUM(K5:K12) | L13: =SUM(L5:L12) | M13: =IFERROR(I13/H13,"—") | N13: =IFERROR(I13/J13,"—") | O13: =SUM(O5:O12) | P13: =SUM(P5:P12) | Q13: =SUM(Q5:Q12) | R13: =IFERROR((E13-I13)/(E13-J13),"—")
B15: PV = quanto deveria ter sido feito | EV = quanto foi feito (em R$) | AC = quanto foi gasto | SPI < 1 atrasado | CPI < 1 acima do custo | EAC = custo total projetado | VAC = desvio final previsto
B17: CURVA S — VALORES ACUMULADOS (R$ mil)
B18: Mês | C18: Mar | D18: Abr | E18: Mai | F18: Jun | G18: Jul | H18: Ago | I18: Set | J18: Out
B19: PV — Valor Planejado | C19: 35 | D19: 120 | E19: 245 | F19: 390 | G19: 540 | H19: 660 | I19: 780 | J19: 850
B20: EV — Valor Agregado | C20: 33 | D20: 112 | E20: 228 | F20: 352
B21: AC — Custo Real | C21: 36 | D21: 121 | E21: 248 | F21: 374

Sheet ⚠️ Riscos
A1: REGISTRO DE RISCOS — ANÁLISE QUALITATIVA (PROBABILIDADE × IMPACTO)
A3: ID | B3: Data | C3: Categoria | D3: Descrição do Risco (causa → evento → efeito) | E3: Prob. (1-5) | F3: Imp. (1-5) | G3: Score (auto) | H3: Nível (auto) | I3: Estratégia | J3: Plano de Resposta | K3: Responsável | L3: Status | M3: Custo da Resposta | N3: Próxima Revisão | O3: Exposição (R$, auto) | Q3: MATRIZ DE RISCOS 5×5 (contagem automática)
A4: R-01 | B4: 46101 | C4: Técnico | D4: Qualidade dos dados legados abaixo do esperado pode atrasar a migração e o go-live | E4: 4 | F4: 5 | G4: =IF(OR(E4="",F4=""),"",E4*F4) | H4: =IF(G4="","",IF(G4>=20,"🔴 Crítico",IF(G4>=12,"🟠 Alto",IF(G4>=6,"🟡 Moderado","🟢 Baixo")))) | I4: Mitigar | J4: Auditoria de dados antecipada; 3 cargas de teste; equipe extra de limpeza contratada | K4: Roberto Lima | L4: Em Tratamento | M4: 25000 | N4: 46199 | O4: =IF(OR(E4="",F4=""),"",E4/5*F4/5*'📋 TAP'!$C$10) | Q4: PROBABILIDADE ↓ / IMPACTO → | R4: 1 | S4: 2 | T4: 3 | U4: 4 | V4: 5
A5: R-02 | B5: 46101 | C5: Organizacional | D5: Indisponibilidade dos key users nas fases de parametrização e testes | E5: 4 | F5: 4 | G5: =IF(OR(E5="",F5=""),"",E5*F5) | H5: =IF(G5="","",IF(G5>=20,"🔴 Crítico",IF(G5>=12,"🟠 Alto",IF(G5>=6,"🟡 Moderado","🟢 Baixo")))) | I5: Mitigar | J5: Acordo formal de 50% de alocação assinado pelos diretores; agenda bloqueada com 4 semanas de antecedência | K5: Ana B. Souza | L5: Em Tratamento | M5: 0 | N5: 46192 | O5: =IF(OR(E5="",F5=""),"",E5/5*F5/5*'📋 TAP'!$C$10) | Q5: 5 | R5: =COUNTIFS($E$4:$E$33,5,$F$4:$F$33,1,$L$4:$L$33,"<>Encerrado") | S5: =COUNTIFS($E$4:$E$33,5,$F$4:$F$33,2,$L$4:$L$33,"<>Encerrado") | T5: =COUNTIFS($E$4:$E$33,5,$F$4:$F$33,3,$L$4:$L$33,"<>Encerrado") | U5: =COUNTIFS($E$4:$E$33,5,$F$4:$F$33,4,$L$4:$L$33,"<>Encerrado") | V5: =COUNTIFS($E$4:$E$33,5,$F$4:$F$33,5,$L$4:$L$33,"<>Encerrado")
A6: R-03 | B6: 46106 | C6: Comercial | D6: Atraso do fornecedor na entrega das customizações contratadas | E6: 3 | F6: 4 | G6: =IF(OR(E6="",F6=""),"",E6*F6) | H6: =IF(G6="","",IF(G6>=20,"🔴 Crítico",IF(G6>=12,"🟠 Alto",IF(G6>=6,"🟡 Moderado","🟢 Baixo")))) | I6: Transferir | J6: Multa contratual por atraso; marcos de pagamento vinculados a entregas aceitas | K6: Ana B. Souza | L6: Aberto | M6: 0 | N6: 46206 | O6: =IF(OR(E6="",F6=""),"",E6/5*F6/5*'📋 TAP'!$C$10) | Q6: 4 | R6: =COUNTIFS($E$4:$E$33,4,$F$4:$F$33,1,$L$4:$L$33,"<>Encerrado") | S6: =COUNTIFS($E$4:$E$33,4,$F$4:$F$33,2,$L$4:$L$33,"<>Encerrado") | T6: =COUNTIFS($E$4:$E$33,4,$F$4:$F$33,3,$L$4:$L$33,"<>Encerrado") | U6: =COUNTIFS($E$4:$E$33,4,$F$4:$F$33,4,$L$4:$L$33,"<>Encerrado") | V6: =COUNTIFS($E$4:$E$33,4,$F$4:$F$33,5,$L$4:$L$33,"<>Encerrado")
A7: R-04 | B7: 46114 | C7: Técnico | D7: Integração com o sistema fiscal legado mais complexa que o estimado | E7: 3 | F7: 3 | G7: =IF(OR(E7="",F7=""),"",E7*F7) | H7: =IF(G7="","",IF(G7>=20,"🔴 Crítico",IF(G7>=12,"🟠 Alto",IF(G7>=6,"🟡 Moderado","🟢 Baixo")))) | I7: Mitigar | J7: Prova de conceito da integração antes do desenvolvimento; consultor especialista sob demanda | K7: Diego Martins | L7: Em Tratamento | M7: 18000 | N7: 46203 | O7: =IF(OR(E7="",F7=""),"",E7/5*F7/5*'📋 TAP'!$C$10) | Q7: 3 | R7: =COUNTIFS($E$4:$E$33,3,$F$4:$F$33,1,$L$4:$L$33,"<>Encerrado") | S7: =COUNTIFS($E$4:$E$33,3,$F$4:$F$33,2,$L$4:$L$33,"<>Encerrado") | T7: =COUNTIFS($E$4:$E$33,3,$F$4:$F$33,3,$L$4:$L$33,"<>Encerrado") | U7: =COUNTIFS($E$4:$E$33,3,$F$4:$F$33,4,$L$4:$L$33,"<>Encerrado") | V7: =COUNTIFS($E$4:$E$33,3,$F$4:$F$33,5,$L$4:$L$33,"<>Encerrado")
A8: R-05 | B8: 46122 | C8: Externo | D8: Mudança na legislação fiscal exigindo reparametrização | E8: 2 | F8: 4 | G8: =IF(OR(E8="",F8=""),"",E8*F8) | H8: =IF(G8="","",IF(G8>=20,"🔴 Crítico",IF(G8>=12,"🟠 Alto",IF(G8>=6,"🟡 Moderado","🟢 Baixo")))) | I8: Aceitar | J8: Monitorar publicações; reserva de contingência cobre até 200 h de ajustes | K8: Fernanda Costa | L8: Aberto | M8: 0 | N8: 46234 | O8: =IF(OR(E8="",F8=""),"",E8/5*F8/5*'📋 TAP'!$C$10) | Q8: 2 | R8: =COUNTIFS($E$4:$E$33,2,$F$4:$F$33,1,$L$4:$L$33,"<>Encerrado") | S8: =COUNTIFS($E$4:$E$33,2,$F$4:$F$33,2,$L$4:$L$33,"<>Encerrado") | T8: =COUNTIFS($E$4:$E$33,2,$F$4:$F$33,3,$L$4:$L$33,"<>Encerrado") | U8: =COUNTIFS($E$4:$E$33,2,$F$4:$F$33,4,$L$4:$L$33,"<>Encerrado") | V8: =COUNTIFS($E$4:$E$33,2,$F$4:$F$33,5,$L$4:$L$33,"<>Encerrado")
A9: R-06 | B9: 46127 | C9: Organizacional | D9: Resistência dos usuários à mudança reduz adoção pós go-live | E9: 3 | F9: 3 | G9: =IF(OR(E9="",F9=""),"",E9*F9) | H9: =IF(G9="","",IF(G9>=20,"🔴 Crítico",IF(G9>=12,"🟠 Alto",IF(G9>=6,"🟡 Moderado","🟢 Baixo")))) | I9: Mitigar | J9: Plano de gestão da mudança; champions por área; comunicação quinzenal | K9: Fernanda Costa | L9: Em Tratamento | M9: 12000 | N9: 46213 | O9: =IF(OR(E9="",F9=""),"",E9/5*F9/5*'📋 TAP'!$C$10) | Q9: 1 | R9: =COUNTIFS($E$4:$E$33,1,$F$4:$F$33,1,$L$4:$L$33,"<>Encerrado") | S9: =COUNTIFS($E$4:$E$33,1,$F$4:$F$33,2,$L$4:$L$33,"<>Encerrado") | T9: =COUNTIFS($E$4:$E$33,1,$F$4:$F$33,3,$L$4:$L$33,"<>Encerrado") | U9: =COUNTIFS($E$4:$E$33,1,$F$4:$F$33,4,$L$4:$L$33,"<>Encerrado") | V9: =COUNTIFS($E$4:$E$33,1,$F$4:$F$33,5,$L$4:$L$33,"<>Encerrado")
A10: R-07 | B10: 46147 | C10: Gerenciamento | D10: Estouro de horas de customização além das 400 h contratadas | E10: 3 | F10: 4 | G10: =IF(OR(E10="",F10=""),"",E10*F10) | H10: =IF(G10="","",IF(G10>=20,"🔴 Crítico",IF(G10>=12,"🟠 Alto",IF(G10>=6,"🟡 Moderado","🟢 Baixo")))) | I10: Mitigar | J10: Comitê de mudanças rigoroso; backlog priorizado; relatório semanal de consumo de horas | K10: Ana B. Souza | L10: Em Tratamento | M10: 0 | N10: 46195 | O10: =IF(OR(E10="",F10=""),"",E10/5*F10/5*'📋 TAP'!$C$10)
A11: R-08 | B11: 46154 | C11: Técnico | D11: Performance inadequada do ambiente cloud em picos de carga | E11: 2 | F11: 3 | G11: =IF(OR(E11="",F11=""),"",E11*F11) | H11: =IF(G11="","",IF(G11>=20,"🔴 Crítico",IF(G11>=12,"🟠 Alto",IF(G11>=6,"🟡 Moderado","🟢 Baixo")))) | I11: Mitigar | J11: Teste de carga antes do go-live; autoscaling configurado | K11: Roberto Lima | L11: Aberto | M11: 8000 | N11: 46248 | O11: =IF(OR(E11="",F11=""),"",E11/5*F11/5*'📋 TAP'!$C$10)
A12: R-09 | B12: 46162 | C12: Externo | D12: Indisponibilidade do consultor sênior do fornecedor (pessoa-chave) | E12: 2 | F12: 4 | G12: =IF(OR(E12="",F12=""),"",E12*F12) | H12: =IF(G12="","",IF(G12>=20,"🔴 Crítico",IF(G12>=12,"🟠 Alto",IF(G12>=6,"🟡 Moderado","🟢 Baixo")))) | I12: Transferir | J12: Cláusula de substituição em 5 dias úteis com profissional equivalente | K12: Ana B. Souza | L12: Aberto | M12: 0 | N12: 46220 | O12: =IF(OR(E12="",F12=""),"",E12/5*F12/5*'📋 TAP'!$C$10)
A13: R-10 | B13: 46174 | C13: Regulatório | D13: Auditoria externa durante o go-live consumindo a equipe de TI | E13: 1 | F13: 3 | G13: =IF(OR(E13="",F13=""),"",E13*F13) | H13: =IF(G13="","",IF(G13>=20,"🔴 Crítico",IF(G13>=12,"🟠 Alto",IF(G13>=6,"🟡 Moderado","🟢 Baixo")))) | I13: Aceitar | J13: Plano de contingência com janela alternativa de go-live em 23/10 | K13: Ana B. Souza | L13: Aberto | M13: 0 | N13: 46269 | O13: =IF(OR(E13="",F13=""),"",E13/5*F13/5*'📋 TAP'!$C$10)
G14: =IF(OR(E14="",F14=""),"",E14*F14) | H14: =IF(G14="","",IF(G14>=20,"🔴 Crítico",IF(G14>=12,"🟠 Alto",IF(G14>=6,"🟡 Moderado","🟢 Baixo"))))
G15: =IF(OR(E15="",F15=""),"",E15*F15) | H15: =IF(G15="","",IF(G15>=20,"🔴 Crítico",IF(G15>=12,"🟠 Alto",IF(G15>=6,"🟡 Moderado","🟢 Baixo"))))
G16: =IF(OR(E16="",F16=""),"",E16*F16) | H16: =IF(G16="","",IF(G16>=20,"🔴 Crítico",IF(G16>=12,"🟠 Alto",IF(G16>=6,"🟡 Moderado","🟢 Baixo"))))
G17: =IF(OR(E17="",F17=""),"",E17*F17) | H17: =IF(G17="","",IF(G17>=20,"🔴 Crítico",IF(G17>=12,"🟠 Alto",IF(G17>=6,"🟡 Moderado","🟢 Baixo"))))
G18: =IF(OR(E18="",F18=""),"",E18*F18) | H18: =IF(G18="","",IF(G18>=20,"🔴 Crítico",IF(G18>=12,"🟠 Alto",IF(G18>=6,"🟡 Moderado","🟢 Baixo"))))
G19: =IF(OR(E19="",F19=""),"",E19*F19) | H19: =IF(G19="","",IF(G19>=20,"🔴 Crítico",IF(G19>=12,"🟠 Alto",IF(G19>=6,"🟡 Moderado","🟢 Baixo"))))
G20: =IF(OR(E20="",F20=""),"",E20*F20) | H20: =IF(G20="","",IF(G20>=20,"🔴 Crítico",IF(G20>=12,"🟠 Alto",IF(G20>=6,"🟡 Moderado","🟢 Baixo"))))
G21: =IF(OR(E21="",F21=""),"",E21*F21) | H21: =IF(G21="","",IF(G21>=20,"🔴 Crítico",IF(G21>=12,"🟠 Alto",IF(G21>=6,"🟡 Moderado","🟢 Baixo"))))
G22: =IF(OR(E22="",F22=""),"",E22*F22) | H22: =IF(G22="","",IF(G22>=20,"🔴 Crítico",IF(G22>=12,"🟠 Alto",IF(G22>=6,"🟡 Moderado","🟢 Baixo"))))
G23: =IF(OR(E23="",F23=""),"",E23*F23) | H23: =IF(G23="","",IF(G23>=20,"🔴 Crítico",IF(G23>=12,"🟠 Alto",IF(G23>=6,"🟡 Moderado","🟢 Baixo"))))
G24: =IF(OR(E24="",F24=""),"",E24*F24) | H24: =IF(G24="","",IF(G24>=20,"🔴 Crítico",IF(G24>=12,"🟠 Alto",IF(G24>=6,"🟡 Moderado","🟢 Baixo"))))
G25: =IF(OR(E25="",F25=""),"",E25*F25) | H25: =IF(G25="","",IF(G25>=20,"🔴 Crítico",IF(G25>=12,"🟠 Alto",IF(G25>=6,"🟡 Moderado","🟢 Baixo"))))
... G33: =IF(OR(E33="",F33=""),"",E33*F33) | H33: =IF(G33="","",IF(G33>=20,"🔴 Crítico",IF(G33>=12,"🟠 Alto",IF(G33>=6,"🟡 Moderado","🟢 Baixo"))))

Sheet 👥 Stakeholders
A1: REGISTRO DE PARTES INTERESSADAS — MATRIZ PODER × INTERESSE
A3: ID | B3: Nome | C3: Cargo / Organização | D3: Papel no Projeto | E3: Poder (1-5) | F3: Interesse (1-5) | G3: Quadrante (auto) | H3: Engajamento Atual | I3: Engajamento Desejado | J3: Estratégia de Engajamento | K3: Canal / Frequência | L3: Responsável
A4: S-01 | B4: Carlos Mendes | C4: Diretor de Operações | D4: Patrocinador | E4: 5 | F4: 5 | G4: =IF(OR(E4="",F4=""),"",IF(AND(E4>=3,F4>=3),"🔴 Gerenciar de Perto",IF(E4>=3,"🟠 Manter Satisfeito",IF(F4>=3,"🟡 Manter Informado","🟢 Monitorar")))) | H4: Apoiador | I4: Líder | J4: Reunião executiva quinzenal; decisões de escopo e verba passam por ele | K4: Reunião / quinzenal | L4: Ana B. Souza
A5: S-02 | B5: Marta Oliveira | C5: CFO | D5: Comitê Diretivo | E5: 5 | F5: 3 | G5: =IF(OR(E5="",F5=""),"",IF(AND(E5>=3,F5>=3),"🔴 Gerenciar de Perto",IF(E5>=3,"🟠 Manter Satisfeito",IF(F5>=3,"🟡 Manter Informado","🟢 Monitorar")))) | H5: Neutro | I5: Apoiador | J5: Apresentar ROI e ganhos no fechamento contábil; envolver na aprovação do orçamento | K5: Status report / mensal | L5: Ana B. Souza
A6: S-03 | B6: Paulo Ferreira | C6: Gerente de TI | D6: Líder técnico interno | E6: 4 | F6: 5 | G6: =IF(OR(E6="",F6=""),"",IF(AND(E6>=3,F6>=3),"🔴 Gerenciar de Perto",IF(E6>=3,"🟠 Manter Satisfeito",IF(F6>=3,"🟡 Manter Informado","🟢 Monitorar")))) | H6: Apoiador | I6: Apoiador | J6: Envolver nas decisões de arquitetura e infraestrutura | K6: Daily técnica / semanal | L6: Roberto Lima
A7: S-04 | B7: Key users (12) | C7: Coordenadores das áreas | D7: Validação dos processos | E7: 3 | F7: 5 | G7: =IF(OR(E7="",F7=""),"",IF(AND(E7>=3,F7>=3),"🔴 Gerenciar de Perto",IF(E7>=3,"🟠 Manter Satisfeito",IF(F7>=3,"🟡 Manter Informado","🟢 Monitorar")))) | H7: Resistente | I7: Apoiador | J7: Workshops de cocriação; reconhecer esforço junto às diretorias; plano de gestão da mudança | K7: Workshop / semanal | L7: Fernanda Costa
A8: S-05 | B8: Usuários finais (320) | C8: Operação | D8: Usuários do sistema | E8: 1 | F8: 4 | G8: =IF(OR(E8="",F8=""),"",IF(AND(E8>=3,F8>=3),"🔴 Gerenciar de Perto",IF(E8>=3,"🟠 Manter Satisfeito",IF(F8>=3,"🟡 Manter Informado","🟢 Monitorar")))) | H8: Desinformado | I8: Neutro | J8: Comunicação quinzenal; champions por área; treinamento próximo ao go-live | K8: E-mail+intranet / quinzenal | L8: Fernanda Costa
A9: S-06 | B9: TechSolutions | C9: Fornecedor do ERP | D9: Implantadora | E9: 4 | F9: 4 | G9: =IF(OR(E9="",F9=""),"",IF(AND(E9>=3,F9>=3),"🔴 Gerenciar de Perto",IF(E9>=3,"🟠 Manter Satisfeito",IF(F9>=3,"🟡 Manter Informado","🟢 Monitorar")))) | H9: Apoiador | I9: Apoiador | J9: Governança contratual; reunião de steering mensal; SLAs monitorados | K9: Steering / mensal | L9: Ana B. Souza
A10: S-07 | B10: Auditoria Interna | C10: Compliance | D10: Controles e conformidade | E10: 3 | F10: 2 | G10: =IF(OR(E10="",F10=""),"",IF(AND(E10>=3,F10>=3),"🔴 Gerenciar de Perto",IF(E10>=3,"🟠 Manter Satisfeito",IF(F10>=3,"🟡 Manter Informado","🟢 Monitorar")))) | H10: Neutro | I10: Neutro | J10: Informar marcos e evidências de controles; convidar para o UAT | K10: Relatório / por marco | L10: Ana B. Souza
A11: S-08 | B11: Sindicato/RH | C11: Recursos Humanos | D11: Impactos na operação | E11: 2 | F11: 2 | G11: =IF(OR(E11="",F11=""),"",IF(AND(E11>=3,F11>=3),"🔴 Gerenciar de Perto",IF(E11>=3,"🟠 Manter Satisfeito",IF(F11>=3,"🟡 Manter Informado","🟢 Monitorar")))) | H11: Desinformado | I11: Neutro | J11: Comunicado formal sobre mudanças de rotina; canal de dúvidas | K11: Comunicado / por fase | L11: Fernanda Costa
G12: =IF(OR(E12="",F12=""),"",IF(AND(E12>=3,F12>=3),"🔴 Gerenciar de Perto",IF(E12>=3,"🟠 Manter Satisfeito",IF(F12>=3,"🟡 Manter Informado","🟢 Monitorar"))))
G13: =IF(OR(E13="",F13=""),"",IF(AND(E13>=3,F13>=3),"🔴 Gerenciar de Perto",IF(E13>=3,"🟠 Manter Satisfeito",IF(F13>=3,"🟡 Manter Informado","🟢 Monitorar"))))
G14: =IF(OR(E14="",F14=""),"",IF(AND(E14>=3,F14>=3),"🔴 Gerenciar de Perto",IF(E14>=3,"🟠 Manter Satisfeito",IF(F14>=3,"🟡 Manter Informado","🟢 Monitorar"))))
G15: =IF(OR(E15="",F15=""),"",IF(AND(E15>=3,F15>=3),"🔴 Gerenciar de Perto",IF(E15>=3,"🟠 Manter Satisfeito",IF(F15>=3,"🟡 Manter Informado","🟢 Monitorar"))))
G16: =IF(OR(E16="",F16=""),"",IF(AND(E16>=3,F16>=3),"🔴 Gerenciar de Perto",IF(E16>=3,"🟠 Manter Satisfeito",IF(F16>=3,"🟡 Manter Informado","🟢 Monitorar"))))
G17: =IF(OR(E17="",F17=""),"",IF(AND(E17>=3,F17>=3),"🔴 Gerenciar de Perto",IF(E17>=3,"🟠 Manter Satisfeito",IF(F17>=3,"🟡 Manter Informado","🟢 Monitorar"))))
G18: =IF(OR(E18="",F18=""),"",IF(AND(E18>=3,F18>=3),"🔴 Gerenciar de Perto",IF(E18>=3,"🟠 Manter Satisfeito",IF(F18>=3,"🟡 Manter Informado","🟢 Monitorar"))))
G19: =IF(OR(E19="",F19=""),"",IF(AND(E19>=3,F19>=3),"🔴 Gerenciar de Perto",IF(E19>=3,"🟠 Manter Satisfeito",IF(F19>=3,"🟡 Manter Informado","🟢 Monitorar"))))
G20: =IF(OR(E20="",F20=""),"",IF(AND(E20>=3,F20>=3),"🔴 Gerenciar de Perto",IF(E20>=3,"🟠 Manter Satisfeito",IF(F20>=3,"🟡 Manter Informado","🟢 Monitorar"))))
G21: =IF(OR(E21="",F21=""),"",IF(AND(E21>=3,F21>=3),"🔴 Gerenciar de Perto",IF(E21>=3,"🟠 Manter Satisfeito",IF(F21>=3,"🟡 Manter Informado","🟢 Monitorar"))))
G22: =IF(OR(E22="",F22=""),"",IF(AND(E22>=3,F22>=3),"🔴 Gerenciar de Perto",IF(E22>=3,"🟠 Manter Satisfeito",IF(F22>=3,"🟡 Manter Informado","🟢 Monitorar"))))
G23: =IF(OR(E23="",F23=""),"",IF(AND(E23>=3,F23>=3),"🔴 Gerenciar de Perto",IF(E23>=3,"🟠 Manter Satisfeito",IF(F23>=3,"🟡 Manter Informado","🟢 Monitorar"))))
... G26: =IF(OR(E26="",F26=""),"",IF(AND(E26>=3,F26>=3),"🔴 Gerenciar de Perto",IF(E26>=3,"🟠 Manter Satisfeito",IF(F26>=3,"🟡 Manter Informado","🟢 Monitorar"))))

Sheet 🔄 Mudanças
A1: CONTROLE INTEGRADO DE MUDANÇAS (CHANGE LOG)
A3: ID | B3: Data | C3: Solicitante | D3: Descrição da Mudança | E3: Justificativa | F3: Impacto no Escopo | G3: Impacto no Prazo (dias) | H3: Impacto no Custo (R$) | I3: Prioridade | J3: Status | K3: Decisão / Data | L3: Aprovador
A4: MUD-01 | B4: 46134 | C4: Diretoria Comercial | D4: Incluir relatório de comissões customizado no módulo Vendas | E4: Relatório atual é feito manualmente e consome 40 h/mês | F4: Aumenta | G4: 5 | H4: 22000 | I4: 🟡 Média | J4: Aprovada | K4: 46146 | L4: Comitê (CCB)
A5: MUD-02 | B5: 46157 | C5: Key user Financeiro | D5: Alterar fluxo de aprovação de pagamentos para 3 níveis | E5: Política de alçadas revisada pela CFO | F5: Neutro | G5: 3 | H5: 8500 | I5: 🔴 Alta | J5: Aprovada | K5: 46164 | L5: Comitê (CCB)
A6: MUD-03 | B6: 46170 | C6: Gerente de TI | D6: Antecipar integração com e-commerce (fase 2) para o go-live | E6: Oportunidade comercial de fim de ano | F6: Aumenta | G6: 25 | H6: 95000 | I6: 🟡 Média | J6: Rejeitada | K6: 46178 | L6: Patrocinador
A7: MUD-04 | B7: 46181 | C7: Fornecedor | D7: Substituir ferramenta de carga de dados por versão mais recente | E7: Versão atual será descontinuada pelo fabricante | F7: Neutro | G7: 0 | H7: 0 | I7: 🟢 Baixa | J7: Em Análise

Sheet 🚧 Questões
A1: REGISTRO DE QUESTÕES E IMPEDIMENTOS (ISSUE LOG)
A3: ID | B3: Data Abertura | C3: Descrição da Questão | D3: Origem / Relacionada a | E3: Prioridade | F3: Responsável | G3: Prazo | H3: Status | I3: Dias em Aberto (auto) | J3: Alerta (auto) | K3: Resolução
A4: Q-01 | B4: 46160 | C4: De-para de plano de contas com 340 contas sem correspondência | D4: R-01 | E4: 🔴 Alta | F4: Roberto Lima | G4: 46183 | H4: Em Tratamento | I4: =IF(B4="","",IF(H4="Resolvida","—",TODAY()-B4)) | J4: =IF(OR(G4="",H4="Resolvida"),"",IF(TODAY()>G4,"🔴",IF(G4-TODAY()<=5,"🟡","🟢"))) | K4: Workshop com contabilidade agendado; 60% mapeado
A5: Q-02 | B5: 46167 | C5: Key user de Suprimentos alocado em outro projeto da diretoria | D5: R-02 | E5: 🔴 Alta | F5: Ana B. Souza | G5: 46178 | H5: Escalada | I5: =IF(B5="","",IF(H5="Resolvida","—",TODAY()-B5)) | J5: =IF(OR(G5="",H5="Resolvida"),"",IF(TODAY()>G5,"🔴",IF(G5-TODAY()<=5,"🟡","🟢"))) | K5: Escalado ao patrocinador em 01/06
A6: Q-03 | B6: 46174 | C6: Ambiente de QA instável após atualização do fornecedor | D6: 1.2.2 | E6: 🟡 Média | F6: Roberto Lima | G6: 46185 | H6: Em Tratamento | I6: =IF(B6="","",IF(H6="Resolvida","—",TODAY()-B6)) | J6: =IF(OR(G6="",H6="Resolvida"),"",IF(TODAY()>G6,"🔴",IF(G6-TODAY()<=5,"🟡","🟢"))) | K6: Chamado aberto no fornecedor (SLA 5 dias)
A7: Q-04 | B7: 46176 | C7: Definição pendente da política de alçadas para o fluxo de compras | D7: 1.3.2 | E7: 🔴 Alta | F7: Diego Martins | G7: 46192 | H7: Aberta | I7: =IF(B7="","",IF(H7="Resolvida","—",TODAY()-B7)) | J7: =IF(OR(G7="",H7="Resolvida"),"",IF(TODAY()>G7,"🔴",IF(G7-TODAY()<=5,"🟡","🟢")))
A8: Q-05 | B8: 46126 | C8: Acesso VPN dos consultores externos bloqueado pela segurança | D8: 1.2 | E8: 🟡 Média | F8: Paulo Ferreira | G8: 46136 | H8: Resolvida | I8: =IF(B8="","",IF(H8="Resolvida","—",TODAY()-B8)) | J8: =IF(OR(G8="",H8="Resolvida"),"",IF(TODAY()>G8,"🔴",IF(G8-TODAY()<=5,"🟡","🟢"))) | K8: Política de acesso temporário aprovada em 22/04
A9: Q-06 | B9: 46182 | C9: Sala de treinamento indisponível nas datas planejadas de setembro | D9: 1.6 | E9: 🟢 Baixa | F9: Fernanda Costa | G9: 46218 | H9: Aberta | I9: =IF(B9="","",IF(H9="Resolvida","—",TODAY()-B9)) | J9: =IF(OR(G9="",H9="Resolvida"),"",IF(TODAY()>G9,"🔴",IF(G9-TODAY()<=5,"🟡","🟢")))
I10: =IF(B10="","",IF(H10="Resolvida","—",TODAY()-B10)) | J10: =IF(OR(G10="",H10="Resolvida"),"",IF(TODAY()>G10,"🔴",IF(G10-TODAY()<=5,"🟡","🟢")))
I11: =IF(B11="","",IF(H11="Resolvida","—",TODAY()-B11)) | J11: =IF(OR(G11="",H11="Resolvida"),"",IF(TODAY()>G11,"🔴",IF(G11-TODAY()<=5,"🟡","🟢")))
I12: =IF(B12="","",IF(H12="Resolvida","—",TODAY()-B12)) | J12: =IF(OR(G12="",H12="Resolvida"),"",IF(TODAY()>G12,"🔴",IF(G12-TODAY()<=5,"🟡","🟢")))
I13: =IF(B13="","",IF(H13="Resolvida","—",TODAY()-B13)) | J13: =IF(OR(G13="",H13="Resolvida"),"",IF(TODAY()>G13,"🔴",IF(G13-TODAY()<=5,"🟡","🟢")))
I14: =IF(B14="","",IF(H14="Resolvida","—",TODAY()-B14)) | J14: =IF(OR(G14="",H14="Resolvida"),"",IF(TODAY()>G14,"🔴",IF(G14-TODAY()<=5,"🟡","🟢")))
I15: =IF(B15="","",IF(H15="Resolvida","—",TODAY()-B15)) | J15: =IF(OR(G15="",H15="Resolvida"),"",IF(TODAY()>G15,"🔴",IF(G15-TODAY()<=5,"🟡","🟢")))
I16: =IF(B16="","",IF(H16="Resolvida","—",TODAY()-B16)) | J16: =IF(OR(G16="",H16="Resolvida"),"",IF(TODAY()>G16,"🔴",IF(G16-TODAY()<=5,"🟡","🟢")))
I17: =IF(B17="","",IF(H17="Resolvida","—",TODAY()-B17)) | J17: =IF(OR(G17="",H17="Resolvida"),"",IF(TODAY()>G17,"🔴",IF(G17-TODAY()<=5,"🟡","🟢")))
I18: =IF(B18="","",IF(H18="Resolvida","—",TODAY()-B18)) | J18: =IF(OR(G18="",H18="Resolvida"),"",IF(TODAY()>G18,"🔴",IF(G18-TODAY()<=5,"🟡","🟢")))
I19: =IF(B19="","",IF(H19="Resolvida","—",TODAY()-B19)) | J19: =IF(OR(G19="",H19="Resolvida"),"",IF(TODAY()>G19,"🔴",IF(G19-TODAY()<=5,"🟡","🟢")))
I20: =IF(B20="","",IF(H20="Resolvida","—",TODAY()-B20)) | J20: =IF(OR(G20="",H20="Resolvida"),"",IF(TODAY()>G20,"🔴",IF(G20-TODAY()<=5,"🟡","🟢")))
I21: =IF(B21="","",IF(H21="Resolvida","—",TODAY()-B21)) | J21: =IF(OR(G21="",H21="Resolvida"),"",IF(TODAY()>G21,"🔴",IF(G21-TODAY()<=5,"🟡","🟢")))
... I29: =IF(B29="","",IF(H29="Resolvida","—",TODAY()-B29)) | J29: =IF(OR(G29="",H29="Resolvida"),"",IF(TODAY()>G29,"🔴",IF(G29-TODAY()<=5,"🟡","🟢")))

Sheet 📚 Lições
A1: LIÇÕES APRENDIDAS — REGISTRE DURANTE O PROJETO, NÃO SÓ NO FIM
A3: ID | B3: Data | C3: Fase | D3: Categoria | E3: O que aconteceu | F3: O que funcionou / não funcionou | G3: Recomendação para projetos futuros | H3: Impacto | I3: Autor
A4: LA-01 | B4: 46127 | C4: Planejamento | D4: Pessoas | E4: Workshops de levantamento com todas as áreas juntas geravam dispersão | F4: Sessões separadas por área, com pauta fechada, foram 2× mais produtivas | G4: Planejar workshops por área desde o início, com no máximo 8 participantes | H4: 🟢 Positivo | I4: Fernanda Costa
A5: LA-02 | B5: 46152 | C5: Execução | D5: Fornecedores | E5: Contrato sem critério objetivo de 'entrega aceita' gerou disputa no 1º pagamento | F5: Não funcionou: aceite implícito. Funcionou: addendum com checklist de aceitação | G5: Definir critérios de aceitação mensuráveis em contrato, antes da assinatura | H5: 🔴 Negativo | I5: Ana B. Souza
A6: LA-03 | B6: 46170 | C6: Execução | D6: Tecnologia | E6: Carga de teste antecipada revelou problemas de dados 3 meses antes do previsto | F6: Antecipar a 1ª carga de teste deu tempo hábil para corrigir a qualidade dos dados | G6: Sempre executar uma carga de dados exploratória na primeira metade do projeto | H6: 🟢 Positivo | I6: Roberto Lima
A7: LA-04 | B7: 46178 | C7: Execução | D7: Comunicação | E7: Boletim quinzenal por e-mail tinha baixa leitura (18%) | F7: Mural na intranet + 5 min nas reuniões de equipe das áreas funcionou melhor | G7: Validar o canal de comunicação com uma amostra de usuários antes de padronizar | H7: 🟡 Neutro | I7: Fernanda Costa

Sheet 📖 Ajuda
B2: PLANILHA DE GERENCIAMENTO DE PROJETOS — PMI / PMBOK
B4: ABA | C4: COMO USAR
B5: Dashboard | C5: Visão executiva automática: saúde do projeto, SPI/CPI, avanço físico, riscos, questões e Curva S. NADA é digitado aqui — tudo é calculado das demais abas.
B6: TAP | C6: Termo de Abertura do Projeto (Project Charter). Preencha no início: objetivo, escopo, premissas, restrições, marcos e orçamento. As datas e o nome do projeto alimentam o Dashboard.
B7: EAP | C7: Estrutura Analítica do Projeto (WBS). Decomponha as entregas usando códigos hierárquicos (1, 1.1, 1.1.1...). Use os mesmos códigos no Cronograma e no EVM.
B8: Cronograma | C8: Plano de trabalho com Gantt automático: informe Início, Término e % Concluído — a Duração, o Status (Atrasada/Em Andamento/Concluída) e as barras do Gantt são calculados sozinhos. A semana atual fica destacada no cabeçalho.
B9: EVM | C9: Gerenciamento de Valor Agregado: informe o orçamento (BAC), o % real e o custo real (AC) de cada pacote — PV, EV, SV, CV, SPI, CPI, EAC, ETC, VAC e TCPI são calculados automaticamente.
B10: Riscos | C10: Registro de riscos: avalie Probabilidade × Impacto (1 a 5) e a planilha calcula o score, o nível (Baixo→Crítico) e atualiza a Matriz de Riscos 5×5 ao lado.
B11: Stakeholders | C11: Registro de partes interessadas: classifique Poder × Interesse (1 a 5) e a estratégia de engajamento (Gerenciar de Perto, Manter Satisfeito...) é sugerida automaticamente.
B12: Mudanças | C12: Log de solicitações de mudança com impacto em escopo, prazo e custo, e fluxo de aprovação.
B13: Questões | C13: Issue log: pendências e impedimentos do dia a dia, com cálculo automático de dias em aberto e alerta visual para itens estourados.
B14: Lições | C14: Lições aprendidas, registradas durante o projeto (não só no fim!), por fase e categoria.
B16: LEGENDA DE SAÚDE
B17: 🟢 NO RUMO | C17: SPI e CPI ≥ 0,95 — projeto dentro do prazo e do orçamento.
B18: 🟡 ATENÇÃO | C18: SPI ou CPI entre 0,85 e 0,95 — desvios moderados, agir preventivamente.
B19: 🔴 CRÍTICO | C19: SPI ou CPI < 0,85 — desvio relevante, exige plano de recuperação.

Sheet Listas
A1: ListaStatus | B1: ListaPrioridade | C1: ListaSimNao | D1: ListaCatRisco | E1: ListaEstrategia | F1: ListaStatusRisco | G1: ListaStatusMudanca | H1: ListaStatusQuestao | I1: ListaEngajamento | J1: ListaFase | K1: ListaCatLicao | L1: Lista15
A2: ⚪ Não Iniciada | B2: 🔴 Alta | C2: Sim | D2: Técnico | E2: Mitigar | F2: Aberto | G2: Em Análise | H2: Aberta | I2: Desinformado | J2: Iniciação | K2: Processo | L2: 1
A3: 🟡 Em Andamento | B3: 🟡 Média | C3: Não | D3: Externo | E3: Transferir | F3: Em Tratamento | G3: Aprovada | H3: Em Tratamento | I3: Resistente | J3: Planejamento | K3: Pessoas | L3: 2
A4: ✅ Concluída | B4: 🟢 Baixa | D4: Organizacional | E4: Aceitar | F4: Materializado | G4: Rejeitada | H4: Resolvida | I4: Neutro | J4: Execução | K4: Tecnologia | L4: 3
A5: 🔴 Atrasada | D5: Gerenciamento | E5: Eliminar | F5: Encerrado | G5: Adiada | H5: Escalada | I5: Apoiador | J5: Monitoramento | K5: Fornecedores | L5: 4
A6: ⏸ Suspensa | D6: Comercial | E6: Explorar | G6: Implementada | I6: Líder | J6: Encerramento | K6: Comunicação | L6: 5
D7: Regulatório | E7: Compartilhar | K7: Riscos
